Workbook

Sheet 📊 Overview
A1: 🚀 MASTER LEARNING DASHBOARD
A2: 1-Year Master Copy • Murex Zero → Advanced + Python / Linux / Shell / Networking / AWS / DevOps
A4: 🎯 Career Stack
A5: MUREX + PYTHON + LINUX + SHELL + NETWORKING + SQL + APIs + AWS/CLOUD + DEVOPS + AUTOMATION
A8: Murex Functional | C8: Murex Technical | E8: Python | G8: Linux + Shell
A9: 59 | C9: 55 | E9: 58 | G9: 56
A11: Networking | C11: AWS / Cloud | E11: DevOps | G11: Total Concepts
A12: 33 | C12: 42 | E12: 56 | G12: 359
A15: 📌 MASTER ROADMAP RULES
A16: 1. Murex is the primary career track; the technical stack supports Murex, production engineering and fallback opportunities.
A17: 2. Learn one concept at a time: understand → make notes → hands-on → troubleshooting → interview explanation.
A18: 3. Do not chase every tool. Depth in Python/Linux/Shell/Networking/AWS/DevOps + Murex is more valuable than tool collecting.
A19: 4. Murex labs are training simulations unless you have access to a real MX.3 environment; never claim simulated experience as production experience.
A20: 5. Use the Status column as the single source of truth. Use Notes for interview questions, mistakes, commands and production scenarios.
A22: 🗺️ RECOMMENDED MASTER ORDER
A23: 1️⃣ Python + APIs → 2️⃣ Banking / Murex Functional foundation → 3️⃣ Linux → 4️⃣ Shell → 5️⃣ Networking → 6️⃣ SQL
A24: 7️⃣ AWS / Cloud → 8️⃣ DevOps → 9️⃣ Murex Technical → 🔟 Integrated Production Support + Automation → AI later
A27: 📈 STATUS TRACKING
A28: Track | B28: Total Concepts | C28: Completed | D28: Learning | E28: Practicing | F28: Needs Revision | G28: Not Started | I28: Status | J28: Count
A29: Python | B29: 58 | C29: =COUNTIF('🐍 Python'!G:G,"Completed") | D29: =COUNTIF('🐍 Python'!G:G,"Learning") | E29: =COUNTIF('🐍 Python'!G:G,"Practicing") | F29: =COUNTIF('🐍 Python'!G:G,"Needs Revision") | G29: =COUNTIF('🐍 Python'!G:G,"Not Started") | I29: Completed | J29: =SUM(C29:C36)
A30: Linux | B30: 34 | C30: =COUNTIF('🐧 Linux'!G:G,"Completed") | D30: =COUNTIF('🐧 Linux'!G:G,"Learning") | E30: =COUNTIF('🐧 Linux'!G:G,"Practicing") | F30: =COUNTIF('🐧 Linux'!G:G,"Needs Revision") | G30: =COUNTIF('🐧 Linux'!G:G,"Not Started") | I30: Learning | J30: =SUM(D29:D36)
A31: Shell | B31: 22 | C31: =COUNTIF('🐚 Shell'!G:G,"Completed") | D31: =COUNTIF('🐚 Shell'!G:G,"Learning") | E31: =COUNTIF('🐚 Shell'!G:G,"Practicing") | F31: =COUNTIF('🐚 Shell'!G:G,"Needs Revision") | G31: =COUNTIF('🐚 Shell'!G:G,"Not Started") | I31: Practicing | J31: =SUM(E29:E36)
A32: Networking | B32: 33 | C32: =COUNTIF('🌐 Networking'!G:G,"Completed") | D32: =COUNTIF('🌐 Networking'!G:G,"Learning") | E32: =COUNTIF('🌐 Networking'!G:G,"Practicing") | F32: =COUNTIF('🌐 Networking'!G:G,"Needs Revision") | G32: =COUNTIF('🌐 Networking'!G:G,"Not Started") | I32: Needs Revision | J32: =SUM(F29:F36)
A33: AWS / Cloud | B33: 42 | C33: =COUNTIF('☁️ AWS Cloud'!G:G,"Completed") | D33: =COUNTIF('☁️ AWS Cloud'!G:G,"Learning") | E33: =COUNTIF('☁️ AWS Cloud'!G:G,"Practicing") | F33: =COUNTIF('☁️ AWS Cloud'!G:G,"Needs Revision") | G33: =COUNTIF('☁️ AWS Cloud'!G:G,"Not Started") | I33: Not Started | J33: =SUM(G29:G36)
A34: DevOps | B34: 56 | C34: =COUNTIF('🚀 DevOps'!G:G,"Completed") | D34: =COUNTIF('🚀 DevOps'!G:G,"Learning") | E34: =COUNTIF('🚀 DevOps'!G:G,"Practicing") | F34: =COUNTIF('🚀 DevOps'!G:G,"Needs Revision") | G34: =COUNTIF('🚀 DevOps'!G:G,"Not Started")
A35: Murex Functional | B35: 59 | C35: =COUNTIF('🏦 Murex Functional'!G:G,"Completed") | D35: =COUNTIF('🏦 Murex Functional'!G:G,"Learning") | E35: =COUNTIF('🏦 Murex Functional'!G:G,"Practicing") | F35: =COUNTIF('🏦 Murex Functional'!G:G,"Needs Revision") | G35: =COUNTIF('🏦 Murex Functional'!G:G,"Not Started")
A36: Murex Technical | B36: 55 | C36: =COUNTIF('⚙️ Murex Technical'!G:G,"Completed") | D36: =COUNTIF('⚙️ Murex Technical'!G:G,"Learning") | E36: =COUNTIF('⚙️ Murex Technical'!G:G,"Practicing") | F36: =COUNTIF('⚙️ Murex Technical'!G:G,"Needs Revision") | G36: =COUNTIF('⚙️ Murex Technical'!G:G,"Not Started")

Sheet 📖 How to Use
A1: 📖 HOW TO USE THIS MASTER COPY
A2: This workbook is designed to be your single source of truth for the full technology stack.
A3: Step | B3: Action | C3: Guidance
A4: 1 | B4: Start with 📊 Overview | C4: Use the dashboard to understand the complete stack and track status.
A5: 2 | B5: Use individual concept tabs | C5: Each tab is ordered from basics to advanced. Every row is a concept block with a checklist.
A6: 3 | B6: Use Filters | C6: Every master concept sheet has Excel filters. Filter by Level, Phase, Topic or Status.
A7: 4 | B7: Update Status | C7: Use: Not Started → Learning → Practicing → Completed. Use Needs Revision when a topic is not yet solid.
A8: 5 | B8: Record Notes | C8: Capture commands, mistakes, interview questions, diagrams, production scenarios and links to Git notes.
A9: 6 | B9: Use 📅 52-Week Roadmap | C9: This gives the sequence across the year. It is a guide, not a reason to rush a concept.
A10: 7 | B10: Use 🗓️ Daily Tracker | C10: Record actual minutes and daily tasks. Target around 2 hours/day; adjust when office workload is high.
A11: 8 | B11: Use 🎯 Projects & Interview | C11: Do hands-on projects and incident scenarios. These become your portfolio and interview evidence.
A12: 9 | B12: SQL is included where it matters | C12: SQL is embedded in Python/Murex/AWS/Datamart sections; maintain your separate SQL depth alongside this master copy.
A13: 10 | B13: Murex experience honesty | C13: Training/simulation labs are not real MX.3 production experience. Represent real production experience only when you have it.
A14: 11 | B14: Roadmap stability | C14: Do not keep adding random technologies. Build depth first; add tools only when a role/project genuinely requires them.

Sheet 🐍 Python
A1: 🐍 Python
A2: Python — Basics → Advanced → Automation
A3: # | B3: Level | C3: Phase | D3: Topic | E3: Key Concepts — Master Checklist | F3: Hands-on / Deliverable | G3: Status | H3: Notes / Interview Points
A4: 1 | B4: 01 Basics | C4: Foundation | D4: Python Introduction | E4: What is Python; use cases; Python versions; installation; interpreter; REPL; .py files; IDE/editor; execution flow; interpreter vs compiler; bytecode; PVM | F4: Install Python; run first script; use REPL | G4: Not Started
A5: 2 | B5: 01 Basics | C5: Foundation | D5: Syntax & Structure | E5: Syntax; indentation; comments; statements; expressions; blocks; keywords; identifiers; naming conventions; PEP 8 | F5: Create clean multi-function script | G5: Not Started
A6: 3 | B6: 01 Basics | C6: Foundation | D6: Variables & Objects | E6: Variables; assignment; multiple assignment; constants convention; dynamic typing; strong typing; objects; identity; references; id(); type(); isinstance(); memory basics | F6: Object/reference exercises | G6: Not Started
A7: 4 | B7: 01 Basics | C7: Foundation | D7: Numbers | E7: int; float; complex; arithmetic; abs(); round(); pow(); divmod(); numeric comparisons | F7: Calculator challenge | G7: Not Started
A8: 5 | B8: 01 Basics | C8: Foundation | D8: Boolean & None | E8: True; False; None; truthy/falsy; boolean evaluation | F8: Truth-value challenge | G8: Not Started
A9: 6 | B9: 01 Basics | C9: Foundation | D9: Strings | E9: Quotes; indexing; slicing; immutability; methods; split; join; strip; replace; find; startswith; endswith; formatting; %; format(); f-strings; escapes; raw strings; Unicode; encoding basics | F9: Text parser challenge | G9: Not Started
A10: 7 | B10: 01 Basics | C10: Foundation | D10: Type Conversion | E10: Implicit vs explicit conversion; int; float; str; bool; list; tuple; set; dict | F10: Conversion challenge | G10: Not Started
A11: 8 | B11: 01 Basics | C11: Foundation | D11: Operators | E11: Arithmetic; comparison; logical; assignment; augmented assignment; bitwise; membership; identity; precedence; short-circuit | F11: Operator practice set | G11: Not Started
A12: 9 | B12: 01 Basics | C12: Foundation | D12: Conditionals | E12: if; elif; else; nested conditions; conditional expression/ternary | F12: Decision engine | G12: Not Started
A13: 10 | B13: 01 Basics | C13: Foundation | D13: Loops | E13: for; while; range; nested loops; break; continue; pass; loop else | F13: Loop challenge | G13: Not Started
A14: 11 | B14: 02 Core Data & Functions | C14: Core Python | D14: Lists | E14: Indexing; slicing; update; append; extend; insert; remove; pop; clear; sort; reverse; copy; nested lists | F14: CRUD + nested list project | G14: Not Started
A15: 12 | B15: 02 Core Data & Functions | C15: Core Python | D15: Tuples | E15: Creation; indexing; slicing; packing; unpacking; immutability | F15: Tuple unpacking exercises | G15: Not Started
... A61: 58 | B61: 05 Data & Automation | C61: Professional/Automation | D61: Python + AI | E61: LLM APIs; prompting; structured outputs; embeddings; RAG; function/tool calling; agents; AI automation | F61: AI-assisted ops prototype | G61: Not Started

Sheet 🐧 Linux
A1: 🐧 Linux
A2: Linux / Unix — Basics → Advanced → Production
A3: # | B3: Level | C3: Phase | D3: Topic | E3: Key Concepts — Master Checklist | F3: Hands-on / Deliverable | G3: Status | H3: Notes / Interview Points
A4: 1 | B4: 01 Foundations | C4: Linux Fundamentals | D4: OS Fundamentals | E4: OS; kernel; shell; user/kernel space; processes; filesystem; drivers; syscalls; Linux vs Unix; distributions; RHEL; Ubuntu; Debian; package managers | F4: Draw Linux architecture | G4: Not Started
A5: 2 | B5: 01 Foundations | C5: Linux Fundamentals | D5: Architecture & Boot | E5: Kernel; shell; utilities; apps; boot; init/systemd; services; runlevels/targets; environment | F5: Trace boot/services | G5: Not Started
A6: 3 | B6: 01 Foundations | C6: Linux Fundamentals | D6: Terminal & Bash | E6: Terminal/console; shell; Bash; command execution; PATH; environment variables; history; aliases | F6: Command-line lab | G6: Not Started
A7: 4 | B7: 01 Foundations | C7: Linux Fundamentals | D7: Filesystem | E7: /; /bin; /boot; /dev; /etc; /home; /lib; /opt; /proc; /root; /tmp; /usr; /var | F7: Filesystem exploration | G7: Not Started
A8: 5 | B8: 01 Foundations | C8: Linux Fundamentals | D8: File & Directory Commands | E8: pwd; ls; cd; mkdir; touch; cp; mv; rm; rmdir; cat; less; more; head; tail; file; stat; tree | F8: File-management challenge | G8: Not Started
A9: 6 | B9: 01 Foundations | C9: Linux Fundamentals | D9: Searching | E9: find; locate; which; whereis; type | F9: Find files/processes | G9: Not Started
A10: 7 | B10: 01 Foundations | C10: Linux Fundamentals | D10: Permissions | E10: read/write/execute; owner/group/others; symbolic/numeric; chmod; chown; chgrp | F10: Permission lab | G10: Not Started
A11: 8 | B11: 01 Foundations | C11: Linux Fundamentals | D11: Advanced Permissions | E11: umask; SUID; SGID; sticky bit; ACL; getfacl; setfacl | F11: Secure shared directory | G11: Not Started
A12: 9 | B12: 01 Foundations | C12: Linux Fundamentals | D12: Users & Groups | E12: passwd/group/shadow; useradd/usermod/userdel/groupadd; passwd; id; who; whoami; su; sudo | F12: User/group administration lab | G12: Not Started
A13: 10 | B13: 02 Processes & Operations | C13: Linux Operations | D13: Processes | E13: PID; PPID; parent-child; foreground/background; states; zombie; orphan | F13: Process tree exercise | G13: Not Started
A14: 11 | B14: 02 Processes & Operations | C14: Linux Operations | D14: Process Management | E14: ps; top; htop; pgrep; pkill; kill; killall; nice; renice | F14: Process incident lab | G14: Not Started
A15: 12 | B15: 02 Processes & Operations | C15: Linux Operations | D15: Signals | E15: SIGTERM; SIGKILL; SIGHUP; SIGINT; SIGSTOP; SIGCONT | F15: Graceful termination lab | G15: Not Started
... A37: 34 | B37: 03 Services, Security & Network | C37: Production Linux | D37: Production Troubleshooting | E37: CPU/memory/disk/service/network troubleshooting with realistic command flows | F37: Full Linux incident simulation | G37: Not Started

Sheet 🐚 Shell
A1: 🐚 Shell
A2: Shell / Bash — Basics → Advanced → Automation
A3: # | B3: Level | C3: Phase | D3: Topic | E3: Key Concepts — Master Checklist | F3: Hands-on / Deliverable | G3: Status | H3: Notes / Interview Points
A4: 1 | B4: 01 Shell Basics | C4: Bash Fundamentals | D4: Shell & Bash | E4: Shell types; Bash; execution; shebang; script permissions; running scripts | F4: First Bash script | G4: Not Started
A5: 2 | B5: 01 Shell Basics | C5: Bash Fundamentals | D5: Variables | E5: Local; environment; export; special variables $0,$1,$2,$#,$?,$$,$@,$* | F5: Argument parser | G5: Not Started
A6: 3 | B6: 01 Shell Basics | C6: Bash Fundamentals | D6: I/O | E6: echo; printf; read; stdin; stdout; stderr | F6: Interactive script | G6: Not Started
A7: 4 | B7: 01 Shell Basics | C7: Bash Fundamentals | D7: Operators | E7: Arithmetic; comparison; string; file; logical operators | F7: Validation script | G7: Not Started
A8: 5 | B8: 01 Shell Basics | C8: Bash Fundamentals | D8: Conditionals | E8: if/elif/else; nested; [[ ]]; test; file/string/numeric tests | F8: Health-check conditions | G8: Not Started
A9: 6 | B9: 01 Shell Basics | C9: Bash Fundamentals | D9: case | E9: case statements; patterns; default | F9: Command dispatcher | G9: Not Started
A10: 7 | B10: 01 Shell Basics | C10: Bash Fundamentals | D10: Loops | E10: for; while; until; nested; break; continue | F10: Batch processor | G10: Not Started
A11: 8 | B11: 01 Shell Basics | C11: Bash Fundamentals | D11: Functions | E11: Parameters; args; return; local; output; reuse | F11: Reusable function library | G11: Not Started
A12: 9 | B12: 01 Shell Basics | C12: Bash Fundamentals | D12: Arrays | E12: Indexed arrays; associative arrays; iteration | F12: Server inventory | G12: Not Started
A13: 10 | B13: 02 Shell Engineering | C13: Bash Automation | D13: Text Processing | E13: grep; sed; awk; cut; sort; uniq; tr; wc | F13: Log analyzer | G13: Not Started
A14: 11 | B14: 02 Shell Engineering | C14: Bash Automation | D14: File Automation | E14: Create/copy/move/delete/search; validation; age; size | F14: File validator | G14: Not Started
A15: 12 | B15: 02 Shell Engineering | C15: Bash Automation | D15: Wildcards & Globbing | E15: *; ?; []; brace expansion; globbing | F15: Safe file selection | G15: Not Started
... A25: 22 | B25: 02 Shell Engineering | C25: Bash Automation | D25: Shell Projects | E25: Disk monitor; process monitor; service health; log analyzer; file validator; backup; batch; API health checker; server health report | F25: Build project portfolio | G25: Not Started

Sheet 🌐 Networking
A1: 🌐 Networking
A2: Networking — Basics → Advanced → Production Troubleshooting
A3: # | B3: Level | C3: Phase | D3: Topic | E3: Key Concepts — Master Checklist | F3: Hands-on / Deliverable | G3: Status | H3: Notes / Interview Points
A4: 1 | B4: 01 Networking Basics | C4: Network Foundations | D4: Network Basics | E4: Networks; LAN; WAN; MAN; Internet; Intranet; client-server; P2P; topologies | F4: Draw network types | G4: Not Started
A5: 2 | B5: 01 Networking Basics | C5: Network Foundations | D5: Network Devices | E5: Hub; switch; router; bridge; gateway; modem; AP; firewall; proxy; load balancer | F5: Device-role map | G5: Not Started
A6: 3 | B6: 01 Networking Basics | C6: Network Foundations | D6: OSI Model | E6: All 7 layers; responsibilities; encapsulation; troubleshooting by layer | F6: OSI troubleshooting | G6: Not Started
A7: 4 | B7: 01 Networking Basics | C7: Network Foundations | D7: TCP/IP Model | E7: Model layers; mapping to OSI; protocols by layer | F7: Protocol mapping | G7: Not Started
A8: 5 | B8: 01 Networking Basics | C8: Network Foundations | D8: Ethernet & MAC | E8: Ethernet; MAC; frames; switch; broadcast; unicast; multicast; VLAN basics | F8: Frame journey | G8: Not Started
A9: 6 | B9: 01 Networking Basics | C9: Network Foundations | D9: ARP | E9: ARP; ARP cache; resolution; troubleshooting | F9: ARP lab | G9: Not Started
A10: 7 | B10: 01 Networking Basics | C10: Network Foundations | D10: IPv4 | E10: IP; network/host; subnet; gateway; private/public; loopback; APIPA | F10: Address classification | G10: Not Started
A11: 8 | B11: 01 Networking Basics | C11: Network Foundations | D11: CIDR | E11: /8; /16; /24; network/broadcast/host range | F11: CIDR calculations | G11: Not Started
A12: 9 | B12: 01 Networking Basics | C12: Network Foundations | D12: Subnetting | E12: Network/host counts; VLSM basics | F12: Subnetting exercises | G12: Not Started
A13: 10 | B13: 01 Networking Basics | C13: Network Foundations | D13: IPv6 | E13: Notation; address types; link-local; global; IPv4 vs IPv6 | F13: IPv6 classification | G13: Not Started
A14: 11 | B14: 02 Transport & Core Services | C14: Protocols | D14: TCP | E14: Connection-oriented; handshake; SYN/SYN-ACK/ACK; sequence/ack; retransmission; flow/congestion | F14: TCP handshake analysis | G14: Not Started
A15: 12 | B15: 02 Transport & Core Services | C15: Protocols | D15: TCP States | E15: LISTEN; SYN-SENT; SYN-RECEIVED; ESTABLISHED; FIN-WAIT; TIME-WAIT; CLOSE-WAIT | F15: Socket-state troubleshooting | G15: Not Started
... A36: 33 | B36: 03 Application Security & Troubleshooting | C36: Production Networking | D36: Production Scenarios | E36: DB connectivity; API timeout; SSH unavailable; Murex interface failure | F36: End-to-end RCA | G36: Not Started

Sheet ☁️ AWS Cloud
A1: ☁️ AWS Cloud
A2: Cloud Computing + AWS — Basics → Advanced → Production
A3: # | B3: Level | C3: Phase | D3: Topic | E3: Key Concepts — Master Checklist | F3: Hands-on / Deliverable | G3: Status | H3: Notes / Interview Points
A4: 1 | B4: 01 Cloud & AWS Foundations | C4: Cloud | D4: Cloud Computing | E4: Cloud definition; data centers; scalability; elasticity; availability; reliability; agility; pay-as-you-go; benefits/limits | F4: On-prem vs cloud diagram | G4: Not Started
A5: 2 | B5: 01 Cloud & AWS Foundations | C5: Cloud | D5: Service Models | E5: IaaS; PaaS; SaaS; responsibility boundaries | F5: Compare models | G5: Not Started
A6: 3 | B6: 01 Cloud & AWS Foundations | C6: Cloud | D6: Deployment Models | E6: Public; private; hybrid; multi-cloud; banking hybrid patterns | F6: Banking cloud architecture | G6: Not Started
A7: 4 | B7: 01 Cloud & AWS Foundations | C7: Cloud | D7: Virtualization | E7: Physical server; hypervisor; VM; guest OS; virtual networking; VM isolation | F7: VM architecture | G7: Not Started
A8: 5 | B8: 01 Cloud & AWS Foundations | C8: Cloud | D8: Containers vs VMs | E8: Container; image; runtime; isolation; startup; resources; Kubernetes concept | F8: Compare VM/container | G8: Not Started
A9: 6 | B9: 01 Cloud & AWS Foundations | C9: Cloud | D9: AWS Global Infrastructure | E9: AWS account; regions; availability zones; edge locations; data centers; fault isolation | F9: Region/AZ diagram | G9: Not Started
A10: 7 | B10: 02 Identity & Compute | C10: AWS Core Services | D10: IAM | E10: Root user; IAM user; group; role; policy; permissions; authentication; authorization; least privilege; MFA; access keys; temporary credentials; STS | F10: Least-privilege policy exercise | G10: Not Started
A11: 8 | B11: 02 Identity & Compute | C11: AWS Core Services | D11: EC2 | E11: Instance; AMI; instance types; CPU; memory; storage; network; key pair; security group; user data; lifecycle | F11: Launch/configure EC2 | G11: Not Started
A12: 9 | B12: 02 Identity & Compute | C12: AWS Core Services | D12: EC2 Pricing | E12: On-Demand; Reserved Instances; Savings Plans; Spot; Dedicated Hosts/Instances | F12: Cost comparison | G12: Not Started
A13: 10 | B13: 02 Identity & Compute | C13: AWS Core Services | D13: EBS | E13: Volumes; root/data volumes; types; snapshots; encryption; backup; EBS vs instance store | F13: Attach/backup volume | G13: Not Started
A14: 11 | B14: 02 Identity & Compute | C14: AWS Core Services | D14: AMI | E14: OS image; custom AMI; lifecycle; launch from AMI | F14: Create AMI | G14: Not Started
A15: 12 | B15: 02 Identity & Compute | C15: AWS Core Services | D15: Auto Scaling | E15: ASG; launch template; desired/min/max; scale in/out; policies; health checks | F15: Scaling scenario | G15: Not Started
... A45: 42 | B45: 07 AWS Automation | C45: Cloud Engineering | D45: Infrastructure as Code | E45: IaC; declarative; repeatability; desired state; drift; version control | F45: IaC concept | G45: Not Started

Sheet 🚀 DevOps
A1: 🚀 DevOps
A2: DevOps — Git → CI/CD → Docker → Kubernetes → IaC → SRE
A3: # | B3: Level | C3: Phase | D3: Topic | E3: Key Concepts — Master Checklist | F3: Hands-on / Deliverable | G3: Status | H3: Notes / Interview Points
A4: 1 | B4: 01 DevOps Foundations | C4: DevOps | D4: DevOps Fundamentals | E4: Development vs operations; silos; collaboration; automation; continuous improvement; reliability; feedback | F4: DevOps lifecycle | G4: Not Started
A5: 2 | B5: 01 DevOps Foundations | C5: DevOps | D5: DevOps Principles | E5: Collaboration; automation; CI; CD; deployment; IaC; monitoring; security; reliability | F5: Principle checklist | G5: Not Started
A6: 3 | B6: 01 DevOps Foundations | C6: DevOps | D6: DevOps Lifecycle | E6: Plan; Code; Build; Test; Release; Deploy; Operate; Monitor; Feedback | F6: Map tools to stages | G6: Not Started
A7: 4 | B7: 01 DevOps Foundations | C7: DevOps | D7: Git Fundamentals | E7: Repository; working tree; staging; commit; branch; remote; clone/init/status/add/log/diff/show | F7: Git lab | G7: Not Started
A8: 5 | B8: 01 DevOps Foundations | C8: DevOps | D8: Git Branching | E8: Main; feature; development; release; hotfix; branching strategies | F8: Branching exercise | G8: Not Started
A9: 6 | B9: 01 DevOps Foundations | C9: DevOps | D9: Git Advanced | E9: Merge conflicts; rebase; cherry-pick; reset; revert; stash; tags; hooks; .gitignore | F9: Recovery lab | G9: Not Started
A10: 7 | B10: 01 DevOps Foundations | C10: DevOps | D10: Git Collaboration | E10: Pull request; code review; protected branches; branch policies; CI triggers | F10: PR workflow | G10: Not Started
A11: 8 | B11: 02 Build CI/CD | C11: Delivery | D11: Build Fundamentals | E11: Source; dependencies; compilation; build; packaging; artifacts; artifact repositories | F11: Build pipeline | G11: Not Started
A12: 9 | B12: 02 Build CI/CD | C12: Delivery | D12: Build Tools | E12: pip; requirements.txt; pyproject.toml; Maven; Gradle concepts | F12: Build examples | G12: Not Started
A13: 10 | B13: 02 Build CI/CD | C13: Delivery | D13: Artifact Management | E13: Artifact; repository; version; dependency; binary/package; Artifactory; Nexus; CodeArtifact | F13: Artifact flow | G13: Not Started
A14: 11 | B14: 02 Build CI/CD | C14: Delivery | D14: Continuous Integration | E14: Commit trigger; checkout; build; unit tests; static analysis; package; publish | F14: CI pipeline | G14: Not Started
A15: 12 | B15: 02 Build CI/CD | C15: Delivery | D15: Continuous Delivery | E15: Build once; test; deploy environments; approval; production release | F15: CD pipeline | G15: Not Started
... A59: 56 | B59: 06 AWS + DevOps Integration | C59: Cloud DevOps | D59: Advanced Kubernetes | E59: Helm; Ingress; NetworkPolicy; RBAC; operators; stateful workloads; HPA; cluster autoscaling | F59: Helm/K8s lab | G59: Not Started

Sheet 🏦 Murex Functional
A1: 🏦 Murex Functional
A2: Murex Functional — Banking → MX.3 → Front-to-Back → Advanced
A3: # | B3: Level | C3: Phase | D3: Topic | E3: Key Concepts — Master Checklist | F3: Hands-on / Deliverable | G3: Status | H3: Notes / Interview Points
A4: 1 | B4: 01 Banking & Murex | C4: Functional Foundation | D4: Banking Fundamentals | E4: Commercial; investment; retail; corporate; treasury; capital markets; asset management; wealth; custody; clearing | F4: Banking ecosystem map | G4: Not Started
A5: 2 | B5: 01 Banking & Murex | C5: Functional Foundation | D5: Financial Markets | E5: Money market; FX; fixed income; equity; derivatives; commodity; credit | F5: Market map | G5: Not Started
A6: 3 | B6: 01 Banking & Murex | C6: Functional Foundation | D6: Market Participants | E6: Bank; counterparty; client; broker; exchange; CCP; custodian; clearing agent; central bank; corporate; fund; asset manager | F6: Participant flow | G6: Not Started
A7: 4 | B7: 01 Banking & Murex | C7: Functional Foundation | D7: FO/MO/BO | E7: Sales; trading; execution; booking; risk; P&L; limits; controls; confirmation; settlement; payments; accounting; reconciliation | F7: FO/MO/BO lifecycle | G7: Not Started
A8: 5 | B8: 01 Banking & Murex | C8: Functional Foundation | D8: Murex Overview | E8: Murex; MX.3; why banks use it; cross-asset; front-to-back; risk; treasury; collateral; accounting; Datamart; reporting; integration | F8: Explain MX.3 | G8: Not Started
A9: 6 | B9: 01 Banking & Murex | C9: Functional Foundation | D9: Murex Ecosystem | E9: FO; Risk; BO; Finance; Collateral; Treasury; Datamart; Reporting; Interfaces; users; roles; modules | F9: Ecosystem diagram | G9: Not Started
A10: 7 | B10: 01 Banking & Murex | C10: Functional Foundation | D10: Murex Users & Environments | E10: Trader; sales; ops; risk; finance; treasury; settlement; market data; support; functional/technical consultant; DEV/TEST/SIT/UAT/PRE-PROD/PROD | F10: Role/environment matrix | G10: Not Started
A11: 8 | B11: 02 Trade Lifecycle & Reference Data | C11: Core Functional | D11: Trade Fundamentals | E11: Trade; transaction; order; execution; booking; contract; counterparty; portfolio; book; trade attributes; dates; identifiers | F11: Trade data dictionary | G11: Not Started
A12: 9 | B12: 02 Trade Lifecycle & Reference Data | C12: Core Functional | D12: Trade Lifecycle | E12: Order→execution→capture→validation→enrichment→confirmation→settlement→accounting→position→P&L→risk→reporting | F12: Trace trade end-to-end | G12: Not Started
A13: 10 | B13: 02 Trade Lifecycle & Reference Data | C13: Core Functional | D13: Trade Events & States | E13: New; validated; confirmed; settled; matured; cancelled; amended; trade/payment/fixing/settlement events | F13: State model | G13: Not Started
A14: 11 | B14: 02 Trade Lifecycle & Reference Data | C14: Core Functional | D14: Amendment & Cancellation | E14: Economic/non-economic amendment; correction; cancellation; rebooking; downstream impact | F14: Amendment scenario | G14: Not Started
A15: 12 | B15: 02 Trade Lifecycle & Reference Data | C15: Core Functional | D15: Counterparty Data | E15: Counterparty; legal entity; parent; client; internal/external; classifications | F15: Counterparty model | G15: Not Started
... A62: 59 | B62: 07 Advanced Functional | C62: Advanced | D62: Functional Production Troubleshooting | E62: Trade booking; market data; pricing; P&L; risk; settlement; accounting; Datamart; EOD; reporting issues | F62: Functional RCA | G62: Not Started

Sheet ⚙️ Murex Technical
A1: ⚙️ Murex Technical
A2: Murex Technical — Architecture → MxML → Integration → Production
A3: # | B3: Level | C3: Phase | D3: Topic | E3: Key Concepts — Master Checklist | F3: Hands-on / Deliverable | G3: Status | H3: Notes / Interview Points
A4: 1 | B4: 01 Technical Foundations | C4: Murex Technical | D4: Application Fundamentals | E4: Application; client; server; app server; database server; middleware; service; process; port; protocol; API; message; file; batch job | F4: Layered application diagram | G4: Not Started
A5: 2 | B5: 01 Technical Foundations | C5: Murex Technical | D5: Client-Server | E5: Client; server; request; response; session; connection; authentication; authorization | F5: Trace request | G5: Not Started
A6: 3 | B6: 01 Technical Foundations | C6: Murex Technical | D6: Linux for Murex | E6: Processes; services; filesystem; permissions; environment; logs; CPU; memory; disk; network | F6: Murex Linux checklist | G6: Not Started
A7: 4 | B7: 01 Technical Foundations | C7: Murex Technical | D7: SQL for Murex | E7: SELECT; WHERE; ORDER BY; GROUP BY; HAVING; JOIN; LEFT JOIN; CASE; CTE; subquery; UNION; views; indexes; transactions; locks; execution plans | F7: Production SQL toolkit | G7: Not Started
A8: 5 | B8: 02 MX.3 Architecture & Configuration | C8: Architecture | D8: MX.3 Technical Architecture | E8: Client; application/services; processing; calculation; workflow; integration; Datamart; reporting; database; middleware; logging; monitoring | F8: Technical architecture | G8: Not Started
A9: 6 | B9: 02 MX.3 Architecture & Configuration | C9: Architecture | D9: Murex Components | E9: Application services; processing services; calculation engines; workflow; Datamart; integration; batch; DB; logs; monitoring | F9: Component responsibility map | G9: Not Started
A10: 7 | B10: 02 MX.3 Architecture & Configuration | C10: Architecture | D10: Environments | E10: DEV; TEST; SIT; UAT; PRE-PROD; PROD; isolation; DB; market data; endpoints; credentials; deployment | F10: Environment matrix | G10: Not Started
A11: 8 | B11: 02 MX.3 Architecture & Configuration | C11: Architecture | D11: Configuration Management | E11: Static; reference; product; business rules; workflow; market data; interface; batch; parameters; environment dependencies | F11: Config inventory | G11: Not Started
A12: 9 | B12: 02 MX.3 Architecture & Configuration | C12: Architecture | D12: Static Data Configuration | E12: Counterparties; legal entities; books; portfolios; currencies; calendars; SSI; market-data sources | F12: Static-data support case | G12: Not Started
A13: 10 | B13: 02 MX.3 Architecture & Configuration | C13: Architecture | D13: Product Configuration | E13: Product definition; parameters; cash flows; events; pricing; settlement; accounting configuration | F13: Product config map | G13: Not Started
A14: 11 | B14: 02 MX.3 Architecture & Configuration | C14: Architecture | D14: Environment Configuration | E14: Hostnames; ports; URLs; DB connections; credentials; services; env vars; file paths; logs | F14: Config troubleshooting | G14: Not Started
A15: 12 | B15: 03 Workflow, XML & MxML | C15: Integration Core | D15: Workflow Architecture | E15: Event; state; action; condition; transition; validation; approval; exception | F15: Workflow state machine | G15: Not Started
... A58: 55 | B58: 07 Production Support & Advanced | C58: Advanced Production | D58: Technical Architecture Thinking | E58: Application layer; network; integration; processing; DB; Datamart; reporting; logs | F58: Layered troubleshooting | G58: Not Started

Sheet 📅 52-Week Roadmap
A1: 📅 52-WEEK MASTER ROADMAP
A2: Use this as the yearly sequence; detailed concepts live in the individual track tabs.
A3: Week | B3: Month | C3: Primary Focus | D3: Secondary Focus | E3: Murex Outcome | F3: Technical Outcome | G3: Hands-on / Deliverable | H3: Status
A4: 1 | B4: Oct | C4: Murex: Banking + Capital Markets | D4: Python | E4: Banking/market ecosystem | F4: Python setup + syntax | G4: Banking ecosystem + first Python repo
A5: 2 | B5: Oct | C5: Murex: MX.3 + ecosystem | D5: Python | E5: Explain MX.3 and modules | F5: Variables/types/operators | G5: MX.3 overview notes
A6: 3 | B6: Oct | C6: Murex: Trade fundamentals | D6: Python | E6: Trade data model | F6: Strings/collections | G6: Trade data dictionary
A7: 4 | B7: Oct | C7: Murex: Trade lifecycle | D7: Python | E7: Front-to-back lifecycle | F7: Conditions/loops/functions | G7: Lifecycle diagram
A8: 5 | B8: Nov | C8: Murex: Static/reference data | D8: Python/APIs | E8: Counterparty/book/calendar/SSI | F8: Modules/exceptions/files | G8: Static-data dependency map
A9: 6 | B9: Nov | C9: Murex: FX | D9: Python/APIs | E9: Spot/forward/swap/options | F9: JSON/CSV + APIs | G9: FX lifecycle + API client
A10: 7 | B10: Nov | C10: Murex: Money Market + Rates | D10: Python | E10: MM/IRS/OIS | F10: OOP | G10: Cash-flow model
A11: 8 | B11: Nov | C11: Murex: Fixed Income + Derivatives | D11: Python/APIs | E11: Bonds/options/swaps/futures | F11: Advanced Python + API errors | G11: Product comparison
A12: 9 | B12: Dec | C12: Murex: FO | D12: Linux | E12: Trade capture/blotter/simulation | F12: Linux filesystem/permissions | G12: FO workflow
A13: 10 | B13: Dec | C13: Murex: Market Data | D13: Linux | E13: Curves/vol/fixings | F13: Processes/services/logs | G13: Market-data failure RCA
A14: 11 | B14: Dec | C14: Murex: Pricing/Valuation | D14: Linux | E14: PV/models/valuation | F14: Disk/memory/systemd | G14: Valuation chain
A15: 12 | B15: Dec | C15: Murex: P&L/Positions | D15: Linux | E15: P&L explain | F15: Linux logs/monitoring | G15: P&L scenario
... A55: 52 | B55: Aug | C55: AWS + DevOps + Integration | D55: Murex | E55: VPC/S3/RDS/Lambda/monitoring + DevOps integration | F55: — | G55: Cloud/DevOps capstone

Sheet 🗓️ Daily Tracker
A1: 🗓️ DAILY STUDY TRACKER
A2: Fill this as you study. Target ≈ 2 hours/day; adapt to work load.
A3: Date | B3: Week | C3: Primary Track | D3: Topic | E3: Task / Concept | F3: Planned Min | G3: Actual Min | H3: Status | I3: Notes
A4: 46296 | B4: 1 | C4: Murex | F4: 120 | H4: Not Started
A5: 46297 | B5: 1 | C5: Murex | F5: 120 | H5: Not Started
A6: 46298 | B6: 1 | C6: Murex | F6: 120 | H6: Not Started
A7: 46299 | B7: 1 | C7: Murex | F7: 120 | H7: Not Started
A8: 46300 | B8: 1 | C8: Murex | F8: 120 | H8: Not Started
A9: 46301 | B9: 1 | C9: Murex | F9: 120 | H9: Not Started
A10: 46302 | B10: 1 | C10: Murex | F10: 120 | H10: Not Started
A11: 46303 | B11: 2 | C11: Murex | F11: 120 | H11: Not Started
A12: 46304 | B12: 2 | C12: Murex | F12: 120 | H12: Not Started
A13: 46305 | B13: 2 | C13: Murex | F13: 120 | H13: Not Started
A14: 46306 | B14: 2 | C14: Murex | F14: 120 | H14: Not Started
A15: 46307 | B15: 2 | C15: Murex | F15: 120 | H15: Not Started
... A368: 46660 | B368: 52 | C368: Technical | F368: 120 | H368: Not Started

Sheet 🎯 Projects & Interview
A1: 🎯 PROJECTS + INTERVIEW TRACKER
A2: Build evidence of capability: notes → labs → projects → troubleshooting → interview readiness.
A3: Area | B3: Project / Scenario | C3: Skills Covered | D3: Expected Output | E3: Status | F3: Interview Ready? | G3: Notes
A4: Python | B4: Production log analyzer | C4: Python; regex; files; logging; testing | D4: Git-ready project | E4: Not Started | F4: No
A5: Python/API | B5: API health checker | C5: requests; auth; retries; JSON; logging | D5: CLI/reporting tool | E5: Not Started | F5: No
A6: Python/SQL | B6: Trade reconciliation simulator | C6: Python; SQL; joins; reconciliation | D6: Break report | E6: Not Started | F6: No
A7: Linux/Shell | B7: Server health monitor | C7: Linux; Bash; processes; disk; memory; logs | D7: Monitoring script | E7: Not Started | F7: No
A8: Networking | B8: API timeout RCA | C8: DNS; TCP; ports; TLS; curl; tcpdump | D8: Layered RCA | E8: Not Started | F8: No
A9: AWS | B9: 3-tier application | C9: VPC; ALB; EC2; RDS; IAM; CloudWatch | D9: Architecture + lab | E9: Not Started | F9: No
A10: AWS | B10: Serverless API | C10: API Gateway; Lambda; DynamoDB | D10: Working API | E10: Not Started | F10: No
A11: DevOps | B11: Python CI/CD | C11: Git; Jenkins; Docker; tests | D11: Pipeline + Jenkinsfile | E11: Not Started | F11: No
A12: DevOps | B12: Terraform AWS infrastructure | C12: Terraform; VPC; EC2; SG | D12: IaC repository | E12: Not Started | F12: No
A13: DevOps | B13: Kubernetes deployment | C13: Docker; K8s; service; ingress; probes | D13: Deployment manifests | E13: Not Started | F13: No
A14: Murex Functional | B14: FX front-to-back simulation | C14: Trade lifecycle; pricing; P&L; risk; settlement | D14: Functional case study | E14: Not Started | F14: No
A15: Murex Technical | B15: MxML interface failure | C15: XML; MxML; APIs; Linux; networking | D15: Incident RCA | E15: Not Started | F15: No
... A19: Capstone | B19: Murex Production Engineering Lab | C19: Murex + Python + Linux + Shell + SQL + APIs + AWS + DevOps | D19: Full integrated portfolio | E19: Not Started | F19: No
